vais_frontend/__init__.py
vais_frontend/c.004a7b01.js
vais_frontend/c.004a7b01.js.gz
vais_frontend/c.06c5e585.js
vais_frontend/c.06c5e585.js.gz
vais_frontend/c.0bdb0337.js
vais_frontend/c.0bdb0337.js.gz
vais_frontend/c.0cdff89c.js
vais_frontend/c.0cdff89c.js.gz
vais_frontend/c.1170dac1.js
vais_frontend/c.1170dac1.js.gz
vais_frontend/c.11fce759.js
vais_frontend/c.11fce759.js.gz
vais_frontend/c.14628ea3.js
vais_frontend/c.14628ea3.js.gz
vais_frontend/c.166c4b5c.js
vais_frontend/c.166c4b5c.js.gz
vais_frontend/c.1e4d0185.js
vais_frontend/c.1e4d0185.js.gz
vais_frontend/c.259a5b7b.js
vais_frontend/c.259a5b7b.js.gz
vais_frontend/c.2b12d4b5.js
vais_frontend/c.2ef5c8dd.js
vais_frontend/c.2ef5c8dd.js.gz
vais_frontend/c.3021703a.js
vais_frontend/c.3021703a.js.gz
vais_frontend/c.313d2d5a.js
vais_frontend/c.313d2d5a.js.gz
vais_frontend/c.36f258ab.js
vais_frontend/c.36f258ab.js.gz
vais_frontend/c.3b8f3ca0.js
vais_frontend/c.3b8f3ca0.js.gz
vais_frontend/c.3c6412dd.js
vais_frontend/c.3c6412dd.js.gz
vais_frontend/c.3dd7643c.js
vais_frontend/c.3dd7643c.js.gz
vais_frontend/c.3f5552a4.js
vais_frontend/c.3f5552a4.js.gz
vais_frontend/c.4017ca75.js
vais_frontend/c.4017ca75.js.gz
vais_frontend/c.44ff3154.js
vais_frontend/c.44ff3154.js.gz
vais_frontend/c.4cc25ce4.js
vais_frontend/c.4cc25ce4.js.gz
vais_frontend/c.579d124d.js
vais_frontend/c.579d124d.js.gz
vais_frontend/c.5c00e70e.js
vais_frontend/c.5c00e70e.js.gz
vais_frontend/c.6cdbcb12.js
vais_frontend/c.6cdbcb12.js.gz
vais_frontend/c.6d4d84f1.js
vais_frontend/c.6d4d84f1.js.gz
vais_frontend/c.7312bad4.js
vais_frontend/c.7312bad4.js.gz
vais_frontend/c.73230ac7.js
vais_frontend/c.73230ac7.js.gz
vais_frontend/c.74178c3e.js
vais_frontend/c.74178c3e.js.gz
vais_frontend/c.743a15a1.js
vais_frontend/c.743a15a1.js.gz
vais_frontend/c.7943fa91.js
vais_frontend/c.7943fa91.js.gz
vais_frontend/c.8e28b461.js
vais_frontend/c.8e28b461.js.gz
vais_frontend/c.99c1c4ba.js
vais_frontend/c.99c1c4ba.js.gz
vais_frontend/c.a43b7113.js
vais_frontend-20220519051104.dist-info/LICENSE
vais_frontend-20220519051104.dist-info/METADATA
vais_frontend-20220519051104.dist-info/WHEEL
vais_frontend-20220519051104.dist-info/top_level.txt
vais_frontend-20220519051104.dist-info/RECORD
