Metadata-Version: 2.1
Name: vais-frontend
Version: 20220519051104
Summary: The VAIS frontend
Home-page: https://github.com/Vioneta/vais-frontend
Author: Vioneta (Pvt) Ltd
Author-email: admin@vioneta.com
License: UNKNOWN
Platform: UNKNOWN
License-File: LICENSE
